langmark/__init__.py
langmark/base.py
langmark/code.py
langmark/elements.py
langmark/exceptions.py
langmark/factories.py
langmark/formatting.py
langmark/headings.py
langmark/html.py
langmark/links.py
langmark/lists.py
langmark/marks.py
langmark/metadata.py
langmark/quotes.py
langmark-0.8.0.dist-info/DESCRIPTION.rst
langmark-0.8.0.dist-info/METADATA
langmark-0.8.0.dist-info/RECORD
langmark-0.8.0.dist-info/WHEEL
langmark-0.8.0.dist-info/metadata.json
langmark-0.8.0.dist-info/top_level.txt
